dhwaj/__init__.py
dhwaj/main.py
dhwaj/providers/__init__.py
dhwaj/providers/abtasty.py
dhwaj/providers/algolia.py
dhwaj/providers/amplitude.py
dhwaj/providers/appcenter.py
dhwaj/providers/appinsights.py
dhwaj/providers/aws_cli.py
dhwaj/providers/azure_tenant.py
dhwaj/providers/base.py
dhwaj/providers/bazaarvoice.py
dhwaj/providers/browserstack.py
dhwaj/providers/calendly.py
dhwaj/providers/circleci.py
dhwaj/providers/contentful.py
dhwaj/providers/datadog.py
dhwaj/providers/delighted.py
dhwaj/providers/devianart_secret.py
dhwaj/providers/devianart_token.py
dhwaj/providers/dropbox.py
dhwaj/providers/facebook_app.py
dhwaj/providers/facebook_token.py
dhwaj/providers/fcm.py
dhwaj/providers/firebase_custom.py
dhwaj/providers/freshdesk.py
dhwaj/providers/github_token.py
dhwaj/providers/grafana.py
dhwaj/providers/helpscout.py
dhwaj/providers/heroku.py
dhwaj/providers/hubspot.py
dhwaj/providers/infura.py
dhwaj/providers/instagram_basic.py
dhwaj/providers/instagram_graph.py
dhwaj/providers/ipstack.py
dhwaj/providers/iterable.py
dhwaj/providers/jumpcloud.py
dhwaj/providers/keenio.py
dhwaj/providers/linkedin.py
dhwaj/providers/lokalise.py
dhwaj/providers/loqate.py
dhwaj/providers/mailgun.py
dhwaj/providers/newrelic_nerdgraph.py
dhwaj/providers/newrelic_rest.py
dhwaj/providers/npm_token.py
dhwaj/providers/opsgenie.py
dhwaj/providers/pagerduty.py
dhwaj/providers/paypal.py
dhwaj/providers/pendo.py
dhwaj/providers/pivotal.py
dhwaj/providers/razorpay.py
dhwaj/providers/salesforce.py
dhwaj/providers/saucelabs.py
dhwaj/providers/sendgrid.py
dhwaj/providers/slack_api.py
dhwaj/providers/slack_webhook.py
dhwaj/providers/spotify.py
dhwaj/providers/sqaure.py
dhwaj/providers/teams_webhook.py
dhwaj/providers/travis.py
dhwaj/providers/twilio.py
dhwaj/providers/twitter_api.py
dhwaj/providers/twitter_bearer.py
dhwaj/providers/waketime.py
dhwaj/providers/weglot.py
dhwaj/providers/youtube.py
dhwaj/providers/zapier_webhook.py
dhwaj/utils/__init__.py
dhwaj/utils/colors.py
dhwaj/utils/http.py
dhwaj-0.1.0.dist-info/licenses/LICENSE
dhwaj-0.1.0.dist-info/METADATA
dhwaj-0.1.0.dist-info/WHEEL
dhwaj-0.1.0.dist-info/entry_points.txt
dhwaj-0.1.0.dist-info/top_level.txt
dhwaj-0.1.0.dist-info/RECORD
