Metadata-Version: 2.4
Name: dhwaj
Version: 0.1.0
Summary: Universal API Key & Credential Validator
Author-email: Eshan Singh <r0x4r@yahoo.com>
License: MIT
Project-URL: Homepage, https://github.com/R0X4R/dhwaj
Project-URL: Repository, https://github.com/R0X4R/dhwaj/issues
Project-URL: Issues, https://github.com/R0X4R/dhwaj/issues
Keywords: security,pentest,api,keys,recon,keyhacks
Classifier: Programming Language :: Python :: 3
Classifier: Programming Language :: Python :: 3.10
Classifier: Development Status :: 3 - Alpha
Classifier: Environment :: Console
Classifier: Intended Audience :: Developers
Classifier: Intended Audience :: Information Technology
Classifier: Topic :: Security
Classifier: Topic :: Software Development :: Libraries
Classifier: License :: OSI Approved :: MIT License
Requires-Python: >=3.8
License-File: LICENSE
Requires-Dist: requests>=2.0
Requires-Dist: urllib3>=2.0
Dynamic: license-file
